phriky_units
