Metadata-Version: 1.1
Name: phriky-units
Version: 0.1.39
Summary: Physical unit static analysis tool for C++ +
Home-page: https://github.com/jpwco/phriky_units
Author: John-Paul Ore
Author-email: jore@cse.unl.edu
License: MIT license
Keywords: phriky_units
Platform: UNKNOWN
Classifier: Development Status :: 2 - Pre-Alpha
Classifier: Intended Audience :: Developers
Classifier: License :: OSI Approved :: MIT License
Classifier: Natural Language :: English
Classifier: Programming Language :: Python :: 2.7
